no.1/FSM_Baseball.v
`timescale 1ns/1ns
module FSM_Baseball(
    input Pitch, RSTN, CLK, // 입력: Pitch(0:B, 1:S), RSTN, CLK
    output reg [1:0] Result // 출력: 0(결과 없음), 1(볼넷), 2(아웃)
);
    reg [1:0] state_ball, next_ball; // Ball 상태
    reg [1:0] state_strike, next_strike; // Strike 상태
    reg [1:0] next_Result;

    localparam B0 = 2'd0, B1 = 2'd1, B2 = 2'd2, B3 = 2'd3; // Ball 상태정의
    localparam S0 = 2'd0, S1 = 2'd1, S2 = 2'd2; // Strike 상태정의

    always @(posedge CLK or negedge RSTN) begin // 순차논리: 상태 업데이트
        if(!RSTN) begin // 비동기 리셋: 초기화
            state_ball <= B0;
            state_strike <= S0;
            Result <= 2'b00;
        end
        else begin // 클럭 에지: 상태 전이
            state_ball <= next_ball;
            state_strike <= next_strike;
            Result <= next_Result;
        end
    end

    always @(*) begin // 조합논리: 다음상태 계산
        // 초기설정
        next_ball = state_ball; next_strike = state_strike; next_Result = 2'b00;
        if(Pitch == 1'b0) begin // Ball 입력 시
            if(state_ball == B3) begin // 4-Ball 달성 시 볼넷 처리 및 전체리셋
                next_Result = 2'b01;
                next_ball = B0;
                next_strike = S0;
            end
            else begin // 볼 카운트 증가
                next_ball = state_ball + 1'b1;
            end
        end
        else begin // Strike 입력 시
            if(state_strike == S2) begin // 3-Strike 달성 시 아웃 처리 및 전체리셋
                next_Result = 2'b10;
                next_ball = B0;
                next_strike = S0;
            end
            else begin // 스트라이크 카운트 증가
                next_strike = state_strike + 1'b1;
            end
        end
    end
endmodule

no.1/tb_FSM_Baseball.v
`timescale 1ns/1ns
module tb_FSM_Baseball;
    reg Pitch;
    reg RSTN;
    reg CLK;
    wire [1:0] Result;

    FSM_Baseball u0(
        .Pitch(Pitch),
        .RSTN(RSTN),
        .CLK(CLK),
        .Result(Result)
    );

    always #5 CLK = ~CLK; // 10ns 주기(주파수 100MHz) 클럭 생성

    initial begin
        $dumpfile("FSM_Baseball.vcd");
        $dumpvars(0, tb_FSM_Baseball);
    end
    
    initial begin
        CLK = 0; RSTN = 0; Pitch = 0; // 초기 상태 설정

        #10 RSTN = 1; // 10ns 후 비동기 리셋 해제

        // [시나리오 1] 볼넷 판정 (입력: 0 -> 1 -> 0 -> 0 -> 1 -> 0)
        #5  Pitch = 0; // 1구: Ball (1B-0S)
        #10 Pitch = 1; // 2구: Strike (1B-1S)
        #10 Pitch = 0; // 3구: Ball (2B-1S)
        #10 Pitch = 0; // 4구: Ball (3B-1S)
        #10 Pitch = 1; // 5구: Strike (3B-2S, 풀카운트)
        #10 Pitch = 0; // 6구: Ball -> Result=1(Walk) 출력 및 전체리셋
        
        // [시나리오 2] 삼진 아웃 판정 (입력: 1 -> 1 -> 0 -> 0 -> 0 -> 1)
        #10 Pitch = 1; // 1구: Strike (0B-1S)
        #10 Pitch = 1; // 2구: Strike (0B-2S)
        #10 Pitch = 0; // 3구: Ball (1B-2S)
        #10 Pitch = 0; // 4구: Ball (2B-2S)
        #10 Pitch = 0; // 5구: Ball (3B-2S, 풀카운트)
        #10 Pitch = 1; // 6구: Strike -> Result=2(Out) 출력 및 전체리셋
        
        // [시나리오 3] 삼진 아웃 판정 (입력: 0 -> 1 -> 0 -> 1 -> 0 -> 1)
        #10 Pitch = 0; // 1구: Ball (1B-0S)
        #10 Pitch = 1; // 2구: Strike (1B-1S)
        #10 Pitch = 0; // 3구: Ball (2B-1S)
        #10 Pitch = 1; // 4구: Strike (2B-2S)
        #10 Pitch = 0; // 5구: Ball (3B-2S, 풀카운트)
        #10 Pitch = 1; // 6구: Strike -> Result=2(Out) 출력 및 전체리셋
        
        #10 $finish; // 시뮬레이션 종료
    end
endmodule

no.1/FSM_Baseball.vcd
$date
	Sun Jun 07 00:58:43 2026
$end
$version
	Icarus Verilog
$end
$timescale
	1ns
$end
$scope module tb_FSM_Baseball $end
$var wire 2 ! Result [1:0] $end
$var reg 1 " CLK $end
$var reg 1 # Pitch $end
$var reg 1 $ RSTN $end
$scope module u0 $end
$var wire 1 " CLK $end
$var wire 1 # Pitch $end
$var wire 1 $ RSTN $end
$var reg 2 % Result [1:0] $end
$var reg 2 & next_Result [1:0] $end
$var reg 2 ' next_ball [1:0] $end
$var reg 2 ( next_strike [1:0] $end
$var reg 2 ) state_ball [1:0] $end
$var reg 2 * state_strike [1:0] $end
$upscope $end
$upscope $end
$enddefinitions $end
#0
$dumpvars
b0 *
b0 )
b0 (
b1 '
b0 &
b0 %
0$
0#
0"
b0 !
$end
#5
1"
#10
0"
1$
#15
b10 '
b1 )
1"
#20
0"
#25
b1 *
b10 (
b1 '
1"
1#
#30
0"
#35
b10 )
b11 '
b1 (
1"
0#
#40
0"
#45
b0 (
b0 '
b1 &
b11 )
1"
#50
0"
#55
b10 *
b10 &
b0 (
b0 '
1"
1#
#60
0"
#65
b1 !
b1 %
b0 *
b0 )
b0 &
b0 (
b1 '
1"
0#
#70
0"
#75
b0 !
b0 %
b1 *
b10 (
b0 '
1"
1#
#80
0"
#85
b0 (
b10 &
b10 *
1"
#90
0"
#95
b1 )
b10 '
b0 &
b10 (
1"
0#
#100
0"
#105
b11 '
b10 )
1"
#110
0"
#115
b0 (
b0 '
b1 &
b11 )
1"
#120
0"
#125
b10 !
b10 %
b0 *
b0 )
b0 &
b1 (
b0 '
1"
1#
#130
0"
#135
b0 !
b0 %
b1 )
b10 '
b0 (
1"
0#
#140
0"
#145
b1 *
b10 (
b1 '
1"
1#
#150
0"
#155
b10 )
b11 '
b1 (
1"
0#
#160
0"
#165
b10 &
b10 *
b0 (
b0 '
1"
1#
#170
0"
#175
b11 )
b1 &
b0 (
b0 '
1"
0#
#180
0"
#185
b10 !
b10 %
b0 *
b0 )
b0 &
b1 (
b0 '
1"
1#
#190
0"
#195
b10 (
b0 !
b0 %
b1 *
1"
